pyarsenal/__init__.py
pyarsenal/action.py
pyarsenal/agent.py
pyarsenal/auth.py
pyarsenal/client.py
pyarsenal/exceptions.py
pyarsenal/group.py
pyarsenal/group_action.py
pyarsenal/log.py
pyarsenal/objects.py
pyarsenal/session.py
pyarsenal/target.py
pyarsenal/webhook.py
pyarsenal/tools/__init__.py
pyarsenal/tools/cli.py
pyarsenal/tools/console.py
pyarsenal-1.0.0.dist-info/LICENSE
pyarsenal-1.0.0.dist-info/METADATA
pyarsenal-1.0.0.dist-info/WHEEL
pyarsenal-1.0.0.dist-info/entry_points.txt
pyarsenal-1.0.0.dist-info/top_level.txt
pyarsenal-1.0.0.dist-info/RECORD
