Metadata-Version: 2.1
Name: pyarsenal
Version: 1.0.0
Summary: UNKNOWN
Home-page: https://github.com/kcarretto/pyarsenal
Author: Kyle Carretto
Author-email: kcarretto@gmail.com
License: GNU GENERAL PUBLIC LICENSE
Requires-Dist: prompt-toolkit (==1.0.15)
Requires-Dist: fire (==0.1.3)
Requires-Dist: requests (==2.18.4)
Requires-Dist: colorama (==0.3.9)
